open_radar_data/__init__.py
open_radar_data/dataset.py
open_radar_data/registry.txt
open_radar_data/version.py
open_radar_data/tests/test_dataset.py
open_radar_data-0.4.2.dist-info/LICENSE
open_radar_data-0.4.2.dist-info/METADATA
open_radar_data-0.4.2.dist-info/WHEEL
open_radar_data-0.4.2.dist-info/top_level.txt
open_radar_data-0.4.2.dist-info/RECORD
