Metadata-Version: 2.1
Name: open-radar-data
Version: 0.4.2
Summary: Provides utility functions for accessing data repository for openradar examples/notebooks
Author: Open Radar Team
License: MIT License
Project-URL: homepage, https://github.com/openradar/open-radar-data
Project-URL: documentation, https://github.com/openradar/open-radar-data
Project-URL: repository, https://github.com/openradar/open-radar-data
Project-URL: tracker, https://github.com/openradar/open-radar-data/issues
Keywords: open-radar-data,xradar
Classifier: Development Status :: 2 - Pre-Alpha
Classifier: License :: OSI Approved :: MIT License
Classifier: Natural Language :: English
Classifier: Programming Language :: Python :: 3
Classifier: Programming Language :: Python :: 3.9
Classifier: Programming Language :: Python :: 3.10
Classifier: Programming Language :: Python :: 3.11
Classifier: Topic :: Scientific/Engineering
Classifier: Operating System :: OS Independent
Classifier: Intended Audience :: Science/Research
Requires-Python: >=3.9
License-File: LICENSE
Requires-Dist: pooch
